[
        {
          "id": 1, 
          "category": "celulares", 
          "title": "Samsung Galaxy S21", 
          "price": 114999, 
          "pictureUrl": "https://i.ibb.co/XtBsh47/Samsung-Galaxy-S21.png", 
          "description": "Triple Cámara trasera de 12 MP + 12 MP + 8 MP Cámara Frontal de 32 MP. Infinity-O Display de 6.4",
          "stock": 10
        },
        {
            "id": 2, 
            "category": "celulares", 
            "title": "Samsung Galaxy A03s", 
            "price": 59899, 
            "pictureUrl": "https://i.ibb.co/dcRPCzc/Samsung-Galaxy-A03s.png", 
            "description": "Descubrí infinitas posibilidades para tus fotos con las 3 cámaras principales de tu equipo. Poné a prueba tu creatividad y jugá con la iluminación, diferentes planos y efectos para obtener grandes resultados.",
            "stock": 7
          },
          {
            "id": 3, 
            "category": "celulares", 
            "title": "Apple Iphone 13 pro", 
            "price": 386999, 
            "pictureUrl": "https://i.ibb.co/QdTYTXT/Apple-Iphone-13-pro.png", 
            "description": "Phone 13 Pro Max. El mayor avance en el sistema de cámaras Pro hasta ahora. Pantalla Super Retina XDR con ProMotion que brinda una respuesta más rápida y fluida. Chip A15 Bionic para un rendimiento fuera de serie. Diseño resistente y la mayor duración de batería jamás vista en un iPhone.",
            "stock": 3
          },
          {
            "id": 4, 
            "category": "celulares", 
            "title": "Motorola Edge 20 lite", 
            "price": 68879, 
            "pictureUrl": "https://i.ibb.co/48yDCdW/Motorola-Edge-20-lite.png", 
            "description": "Descubrí infinitas posibilidades para tus fotos con las 3 cámaras principales de tu equipo. Poné a prueba tu creatividad y jugá con la iluminación, diferentes planos y efectos para obtener grandes resultados.",
            "stock": 33
          },
          {
            "id": 5, 
            "category": "camaras", 
            "title": "Nikon kit d7500", 
            "price": 425000, 
            "pictureUrl": "https://i.ibb.co/Yhtz1XP/Nikon-kit-d7500.png", 
            "description": "Nikon fabrica cámaras fotográficas con tecnología de punta y excelencia en la calidad. Sus productos permiten que explores toda tu creatividad, asegurándote calidad en los resultados.",
            "stock": 4
          },
          {
            "id": 6, 
            "category": "camaras", 
            "title": "Canon PowerShot sx540", 
            "price": 109990, 
            "pictureUrl": "https://i.ibb.co/LYCLHPs/Canon-Power-Shot-sx540.png", 
            "description": "La marca japonesa Canon combina calidad y rendimiento en sus productos. No importa si recién comenzás en el mundo de la fotografía o si querés mejorar tu equipo, Canon hará que te enamores de la fotografía.",
            "stock": 8
          },
          {
            "id": 7, 
            "category": "camaras", 
            "title": "Sony H300 Compacta", 
            "price": 39900, 
            "pictureUrl": "https://i.ibb.co/DgWTWjh/Sony-H300-Compacta.png", 
            "description": "Sony, marca líder a nivel mundial en el ámbito de la fotografía, fabrica productos de alta performance, sin descuidar la elegancia en sus diseños.",
            "stock": 14
          },
          {
            "id": 8, 
            "category": "camaras", 
            "title": "kodax Sport Sx540", 
            "price": 6850, 
            "pictureUrl": "https://i.ibb.co/tHBHk9r/9.png", 
            "description": "Esta cámara de un solo uso es ideal para eventos sociales y deportivos. Gracias a su tamaño compacto y peso ligero, podrás llevarla a donde quieras y vivir la emoción de sacar fotos únicas con gran facilidad.",
            "stock": 22
          },
          {
            "id": 9, 
            "category": "consolas", 
            "title": "Microsoft Xbox Serie S", 
            "price": 89999, 
            "pictureUrl": "https://i.ibb.co/Lgyxr1K/11.png", 
            "description": "Esta cámara de un solo uso es ideal para eventos sociales y deportivos. Gracias a su tamaño compacto y peso ligero, podrás llevarla a donde quieras y vivir la emoción de sacar fotos únicas con gran facilidad.",
            "stock": 11
          },
          {
            "id": 10, 
            "category": "consolas", 
            "title": "Sony Playstation 5", 
            "price": 229999, 
            "pictureUrl": "https://i.ibb.co/16jft7y/12.png", 
            "description": "Con tu consola PlayStation 5 tendrás entretenimiento asegurado todos los días. Su tecnología fue creada para poner nuevos retos tanto a jugadores principiantes como expertos.",
            "stock": 11
          }
]
